{"name":"000052","timestamp":0,"index":52,"labels":[{"id":0,"category":"human.pedestrian.adult","box3d":{"dimension":{"width":3.7773598259694534,"length":0.33295763935763123,"height":1.468628},"location":{"x":0.5533484499248748,"y":-2.2419960237038454,"z":-1.108606},"orientation":{"rotationYaw":0,"rotationPitch":0,"rotationRoll":0}}},{"id":1,"category":"human.pedestrian.adult","box3d":{"dimension":{"width":0.24711699796061826,"length":4.459254098539706,"height":1.468628},"location":{"x":2.365539768302743,"y":-0.17884779411280793,"z":-1.108606},"orientation":{"rotationYaw":0,"rotationPitch":0,"rotationRoll":0}}},{"id":2,"category":"human.pedestrian.adult","box3d":{"dimension":{"width":3.8126622542495427,"length":0.3686316721459495,"height":1.468628},"location":{"x":0.6651394728118213,"y":2.068616271551204,"z":-1.108606},"orientation":{"rotationYaw":0,"rotationPitch":0,"rotationRoll":0}}},{"id":3,"category":"human.pedestrian.adult","box3d":{"dimension":{"width":0.2588844740539815,"length":3.424707147678495,"height":1.468628},"location":{"x":-1.4647737000868428,"y":-0.10155405640478643,"z":-1.108606},"orientation":{"rotationYaw":0,"rotationPitch":0,"rotationRoll":0}}},{"id":4,"category":"human.pedestrian.adult","box3d":{"dimension":{"width":0.7413509938818557,"length":0.14269613115326996,"height":1.468628},"location":{"x":3.612892234199199,"y":2.0864532879453623,"z":-1.108606},"orientation":{"rotationYaw":0,"rotationPitch":0,"rotationRoll":0}}}]}