{"name":"000487","timestamp":0,"index":487,"labels":[{"id":0,"category":"human.pedestrian.adult","box3d":{"dimension":{"width":0.1882796174938044,"length":3.756445161983536,"height":1.468628},"location":{"x":-1.384645321089204,"y":-2.589928005142814,"z":-1.108606},"orientation":{"rotationYaw":0,"rotationPitch":0,"rotationRoll":0}}},{"id":1,"category":"human.pedestrian.adult","box3d":{"dimension":{"width":0.19190225032596708,"length":1.5373651606541139,"height":1.468628},"location":{"x":-1.3649633678849074,"y":0.7961653878847126,"z":-1.108606},"orientation":{"rotationYaw":0,"rotationPitch":0,"rotationRoll":0}}},{"id":2,"category":"human.pedestrian.adult","box3d":{"dimension":{"width":2.704077163684088,"length":0.11165221837152761,"height":1.468628},"location":{"x":-0.06526176340449119,"y":1.6249683934887464,"z":-1.108606},"orientation":{"rotationYaw":0,"rotationPitch":0,"rotationRoll":0}}},{"id":3,"category":"human.pedestrian.adult","box3d":{"dimension":{"width":0.1308424434040687,"length":0.6398530975906791,"height":1.468628},"location":{"x":1.3565594549197226,"y":0.3087605115320814,"z":-1.108606},"orientation":{"rotationYaw":0,"rotationPitch":0,"rotationRoll":0}}},{"id":4,"category":"human.pedestrian.adult","box3d":{"dimension":{"width":2.669185845443003,"length":0.15888969537486655,"height":1.468628},"location":{"x":0.01760511741808579,"y":-0.0004302470352263027,"z":-1.108606},"orientation":{"rotationYaw":0,"rotationPitch":0,"rotationRoll":0}}},{"id":5,"category":"human.pedestrian.adult","box3d":{"dimension":{"width":0.10031253994311928,"length":0.48955203439823736,"height":1.468628},"location":{"x":2.6846102554710196,"y":1.4531957498402421,"z":-1.108606},"orientation":{"rotationYaw":0,"rotationPitch":0,"rotationRoll":0}}}]}