{"name":"000448","timestamp":0,"index":448,"labels":[{"id":0,"category":"human.pedestrian.adult","box3d":{"dimension":{"width":0.6537762600474397,"length":0.05562996476759735,"height":1.468628},"location":{"x":-1.662076250196521,"y":-0.2316849714393511,"z":-1.108606},"orientation":{"rotationYaw":0,"rotationPitch":0,"rotationRoll":0}}},{"id":1,"category":"human.pedestrian.adult","box3d":{"dimension":{"width":1.404408262324131,"length":0.07152424041548214,"height":1.468628},"location":{"x":-2.0212496276299907,"y":-0.056847939312616794,"z":-1.108606},"orientation":{"rotationYaw":0,"rotationPitch":0,"rotationRoll":0}}},{"id":2,"category":"human.pedestrian.adult","box3d":{"dimension":{"width":0.20178279631093954,"length":1.2238592248871396,"height":1.468628},"location":{"x":-5.617019057890911,"y":0.6862094472260039,"z":-1.108606},"orientation":{"rotationYaw":0,"rotationPitch":0,"rotationRoll":0}}},{"id":3,"category":"human.pedestrian.adult","box3d":{"dimension":{"width":2.502106674255634,"length":0.09536565388730978,"height":1.468628},"location":{"x":-0.3020602030607964,"y":1.2425090949019764,"z":-1.108606},"orientation":{"rotationYaw":0,"rotationPitch":0,"rotationRoll":0}}},{"id":5,"category":"human.pedestrian.adult","box3d":{"dimension":{"width":0.16949754890118918,"length":1.9311544912180192,"height":1.468628},"location":{"x":-2.001071347998897,"y":-1.1773943724885045,"z":-1.108606},"orientation":{"rotationYaw":0,"rotationPitch":0,"rotationRoll":0}}},{"id":6,"category":"human.pedestrian.adult","box3d":{"dimension":{"width":0.839416432653503,"length":0.20662558342250392,"height":1.468628},"location":{"x":-1.5692561638934888,"y":-2.1429716180975142,"z":-1.108606},"orientation":{"rotationYaw":0,"rotationPitch":0,"rotationRoll":0}}},{"id":7,"category":"human.pedestrian.adult","box3d":{"dimension":{"width":0.1775688607536261,"length":0.2702026860140432,"height":1.468628},"location":{"x":-1.1979758186813625,"y":-2.2621786854566515,"z":-1.108606},"orientation":{"rotationYaw":0,"rotationPitch":0,"rotationRoll":0}}},{"id":8,"category":"human.pedestrian.adult","box3d":{"dimension":{"width":1.477050068996068,"length":0.11125992953519503,"height":1.468628},"location":{"x":-0.43523684862601486,"y":-2.3972800284636735,"z":-1.108606},"orientation":{"rotationYaw":0,"rotationPitch":0,"rotationRoll":0}}},{"id":9,"category":"human.pedestrian.adult","box3d":{"dimension":{"width":0.6618475718998778,"length":0.1589427564788497,"height":1.468628},"location":{"x":0.5857841007073324,"y":-1.8250861051398162,"z":-1.108606},"orientation":{"rotationYaw":0,"rotationPitch":0,"rotationRoll":0}}},{"id":10,"category":"human.pedestrian.adult","box3d":{"dimension":{"width":0.1614262370487518,"length":0.5880881989717428,"height":1.468628},"location":{"x":0.28714556216714365,"y":-2.1032359289778024,"z":-1.108606},"orientation":{"rotationYaw":0,"rotationPitch":0,"rotationRoll":0}}},{"id":4,"category":"human.pedestrian.adult","box3d":{"dimension":{"width":0.17756886075362588,"length":3.083489475689677,"height":1.468628},"location":{"x":0.9247791985097086,"y":-0.28334136729497716,"z":-1.108606},"orientation":{"rotationYaw":0,"rotationPitch":0,"rotationRoll":0}}}]}