{"name":"000469","timestamp":0,"index":469,"labels":[{"id":0,"category":"human.pedestrian.adult","box3d":{"dimension":{"width":2.5916982358176917,"length":0.18119474238588884,"height":1.468628},"location":{"x":-0.3396461355422351,"y":-2.2487667024275044,"z":-1.108606},"orientation":{"rotationYaw":0,"rotationPitch":0,"rotationRoll":0}}},{"id":1,"category":"human.pedestrian.adult","box3d":{"dimension":{"width":0.16869041771594473,"length":1.147566701777292,"height":1.468628},"location":{"x":0.9562029823666092,"y":-1.7051824752698397,"z":-1.108606},"orientation":{"rotationYaw":0,"rotationPitch":0,"rotationRoll":0}}},{"id":2,"category":"human.pedestrian.adult","box3d":{"dimension":{"width":0.25303562657391687,"length":0.10569693305843475,"height":1.468628},"location":{"x":1.0827207956535676,"y":-1.1540484671794302,"z":-1.108606},"orientation":{"rotationYaw":0,"rotationPitch":0,"rotationRoll":0}}},{"id":3,"category":"human.pedestrian.adult","box3d":{"dimension":{"width":0.18402591023557524,"length":1.7666487382624105,"height":1.468628},"location":{"x":1.1785676239012637,"y":-0.3160227836446966,"z":-1.108606},"orientation":{"rotationYaw":0,"rotationPitch":0,"rotationRoll":0}}},{"id":4,"category":"human.pedestrian.adult","box3d":{"dimension":{"width":0.2607033728337338,"length":0.09814715212568959,"height":1.468628},"location":{"x":1.0022094599255036,"y":0.563526695020136,"z":-1.108606},"orientation":{"rotationYaw":0,"rotationPitch":0,"rotationRoll":0}}},{"id":5,"category":"human.pedestrian.adult","box3d":{"dimension":{"width":0.19169365649539027,"length":0.9512723975259136,"height":1.468628},"location":{"x":0.8833593928983612,"y":0.990089317720248,"z":-1.108606},"orientation":{"rotationYaw":0,"rotationPitch":0,"rotationRoll":0}}},{"id":6,"category":"human.pedestrian.adult","box3d":{"dimension":{"width":0.12851215656510306,"length":2.8470385454437075,"height":1.468628},"location":{"x":-1.7385271818020587,"y":0.03000286509407135,"z":-1.108606},"orientation":{"rotationYaw":0,"rotationPitch":0,"rotationRoll":0}}},{"id":7,"category":"human.pedestrian.adult","box3d":{"dimension":{"width":2.4952777066390848,"length":0.06853981683475574,"height":1.468628},"location":{"x":-0.4908883284825162,"y":1.4456136974119145,"z":-1.108606},"orientation":{"rotationYaw":0,"rotationPitch":0,"rotationRoll":0}}}]}